<?xml version="1.0" encoding="UTF-8" standalone="no"?>
<annotation>
    <folder>Images</folder>
    <filename>0518_2300.jpg</filename>
    <source>
        <database>Unknown</database>
    </source>
    <size>
        <width>1280</width>
        <height>720</height>
        <depth>3</depth>
    </size>
    <segmented>0</segmented>
    <object>
        <name>person</name>
        <pose>Unspecified</pose>
        <truncated>0</truncated>
        <difficult>0</difficult>
        <occluded>0</occluded>
        <bndbox>
            <xmin>939</xmin>
            <ymin>189</ymin>
            <xmax>985</xmax>
            <ymax>317</ymax>
        </bndbox>
    </object>
    <object>
        <name>person</name>
        <pose>Unspecified</pose>
        <truncated>0</truncated>
        <difficult>0</difficult>
        <occluded>0</occluded>
        <bndbox>
            <xmin>981</xmin>
            <ymin>174</ymin>
            <xmax>1018</xmax>
            <ymax>315</ymax>
        </bndbox>
    </object>
    <object>
        <name>person</name>
        <pose>Unspecified</pose>
        <truncated>0</truncated>
        <difficult>0</difficult>
        <occluded>0</occluded>
        <bndbox>
            <xmin>1044</xmin>
            <ymin>160</ymin>
            <xmax>1088</xmax>
            <ymax>304</ymax>
        </bndbox>
    </object>
    <object>
        <name>person</name>
        <pose>Unspecified</pose>
        <truncated>0</truncated>
        <difficult>0</difficult>
        <occluded>0</occluded>
        <bndbox>
            <xmin>1074</xmin>
            <ymin>155</ymin>
            <xmax>1122</xmax>
            <ymax>302</ymax>
        </bndbox>
    </object>
    <object>
        <name>person</name>
        <pose>Unspecified</pose>
        <truncated>0</truncated>
        <difficult>0</difficult>
        <occluded>0</occluded>
        <bndbox>
            <xmin>465</xmin>
            <ymin>174</ymin>
            <xmax>522</xmax>
            <ymax>355</ymax>
        </bndbox>
    </object>
    <object>
        <name>person</name>
        <pose>Unspecified</pose>
        <truncated>0</truncated>
        <difficult>0</difficult>
        <occluded>0</occluded>
        <bndbox>
            <xmin>740</xmin>
            <ymin>0</ymin>
            <xmax>965</xmax>
            <ymax>533</ymax>
        </bndbox>
    </object>
    <object>
        <name>helmet-on</name>
        <pose>Unspecified</pose>
        <truncated>0</truncated>
        <difficult>0</difficult>
        <occluded>0</occluded>
        <bndbox>
            <xmin>951</xmin>
            <ymin>188</ymin>
            <xmax>969</xmax>
            <ymax>216</ymax>
        </bndbox>
    </object>
    <object>
        <name>helmet-on</name>
        <pose>Unspecified</pose>
        <truncated>0</truncated>
        <difficult>0</difficult>
        <occluded>0</occluded>
        <bndbox>
            <xmin>484</xmin>
            <ymin>175</ymin>
            <xmax>512</xmax>
            <ymax>209</ymax>
        </bndbox>
    </object>
    <object>
        <name>helmet</name>
        <pose>Unspecified</pose>
        <truncated>0</truncated>
        <difficult>0</difficult>
        <occluded>0</occluded>
        <bndbox>
            <xmin>952</xmin>
            <ymin>189</ymin>
            <xmax>969</xmax>
            <ymax>203</ymax>
        </bndbox>
    </object>
    <object>
        <name>helmet</name>
        <pose>Unspecified</pose>
        <truncated>0</truncated>
        <difficult>0</difficult>
        <occluded>0</occluded>
        <bndbox>
            <xmin>485</xmin>
            <ymin>175</ymin>
            <xmax>512</xmax>
            <ymax>193</ymax>
        </bndbox>
    </object>
    <object>
        <name>helmet-off</name>
        <pose>Unspecified</pose>
        <truncated>0</truncated>
        <difficult>0</difficult>
        <occluded>0</occluded>
        <bndbox>
            <xmin>981</xmin>
            <ymin>173</ymin>
            <xmax>999</xmax>
            <ymax>192</ymax>
        </bndbox>
    </object>
    <object>
        <name>helmet-off</name>
        <pose>Unspecified</pose>
        <truncated>0</truncated>
        <difficult>0</difficult>
        <occluded>0</occluded>
        <bndbox>
            <xmin>1048</xmin>
            <ymin>161</ymin>
            <xmax>1069</xmax>
            <ymax>184</ymax>
        </bndbox>
    </object>
    <object>
        <name>helmet-off</name>
        <pose>Unspecified</pose>
        <truncated>0</truncated>
        <difficult>0</difficult>
        <occluded>0</occluded>
        <bndbox>
            <xmin>739</xmin>
            <ymin>0</ymin>
            <xmax>847</xmax>
            <ymax>109</ymax>
        </bndbox>
    </object>
</annotation>
