<annotation>
	<folder>videoplayback31</folder>
	<filename>0318_8020.jpg</filename>
	<path>D:\安全帽检测\scenario-test2\videoplayback31\0318_8020.jpg</path>
	<source>
		<database>Unknown</database>
	</source>
	<size>
		<width>640</width>
		<height>360</height>
		<depth>3</depth>
	</size>
	<segmented>0</segmented>
	<object>
		<name>helmet</name>
		<pose>Unspecified</pose>
		<truncated>0</truncated>
		<difficult>0</difficult>
		<bndbox>
			<xmin>278</xmin>
			<ymin>126</ymin>
			<xmax>310</xmax>
			<ymax>146</ymax>
		</bndbox>
	</object>
	<object>
		<name>helmet</name>
		<pose>Unspecified</pose>
		<truncated>0</truncated>
		<difficult>0</difficult>
		<bndbox>
			<xmin>394</xmin>
			<ymin>38</ymin>
			<xmax>422</xmax>
			<ymax>59</ymax>
		</bndbox>
	</object>
	<object>
		<name>helmet_on</name>
		<pose>Unspecified</pose>
		<truncated>0</truncated>
		<difficult>0</difficult>
		<bndbox>
			<xmin>393</xmin>
			<ymin>38</ymin>
			<xmax>422</xmax>
			<ymax>78</ymax>
		</bndbox>
	</object>
	<object>
		<name>helmet_on</name>
		<pose>Unspecified</pose>
		<truncated>0</truncated>
		<difficult>0</difficult>
		<bndbox>
			<xmin>276</xmin>
			<ymin>127</ymin>
			<xmax>307</xmax>
			<ymax>149</ymax>
		</bndbox>
	</object>
	<object>
		<name>helmet_off</name>
		<pose>Unspecified</pose>
		<truncated>0</truncated>
		<difficult>0</difficult>
		<bndbox>
			<xmin>318</xmin>
			<ymin>188</ymin>
			<xmax>344</xmax>
			<ymax>207</ymax>
		</bndbox>
	</object>
	<object>
		<name>person</name>
		<pose>Unspecified</pose>
		<truncated>0</truncated>
		<difficult>0</difficult>
		<bndbox>
			<xmin>212</xmin>
			<ymin>188</ymin>
			<xmax>353</xmax>
			<ymax>275</ymax>
		</bndbox>
	</object>
	<object>
		<name>person</name>
		<pose>Unspecified</pose>
		<truncated>0</truncated>
		<difficult>0</difficult>
		<bndbox>
			<xmin>260</xmin>
			<ymin>128</ymin>
			<xmax>316</xmax>
			<ymax>292</ymax>
		</bndbox>
	</object>
	<object>
		<name>person</name>
		<pose>Unspecified</pose>
		<truncated>0</truncated>
		<difficult>0</difficult>
		<bndbox>
			<xmin>377</xmin>
			<ymin>38</ymin>
			<xmax>456</xmax>
			<ymax>336</ymax>
		</bndbox>
	</object>
	<object>
		<name>person</name>
		<pose>Unspecified</pose>
		<truncated>0</truncated>
		<difficult>0</difficult>
		<bndbox>
			<xmin>416</xmin>
			<ymin>90</ymin>
			<xmax>451</xmax>
			<ymax>280</ymax>
		</bndbox>
	</object>
</annotation>
