<?xml version="1.0" encoding="UTF-8" standalone="no"?>
<annotation>
    <folder>Images</folder>
    <filename>0318_14425.jpg</filename>
    <source>
        <database>Unknown</database>
    </source>
    <size>
        <width>1280</width>
        <height>720</height>
        <depth>3</depth>
    </size>
    <segmented>0</segmented>
    <object>
        <name>helmet</name>
        <pose>Unspecified</pose>
        <truncated>0</truncated>
        <difficult>0</difficult>
        <occluded>0</occluded>
        <bndbox>
            <xmin>608</xmin>
            <ymin>311</ymin>
            <xmax>771</xmax>
            <ymax>471</ymax>
        </bndbox>
    </object>
    <object>
        <name>helmet</name>
        <pose>Unspecified</pose>
        <truncated>0</truncated>
        <difficult>0</difficult>
        <occluded>0</occluded>
        <bndbox>
            <xmin>659</xmin>
            <ymin>124</ymin>
            <xmax>776</xmax>
            <ymax>281</ymax>
        </bndbox>
    </object>
    <object>
        <name>helmet</name>
        <pose>Unspecified</pose>
        <truncated>0</truncated>
        <difficult>0</difficult>
        <occluded>0</occluded>
        <bndbox>
            <xmin>286</xmin>
            <ymin>51</ymin>
            <xmax>430</xmax>
            <ymax>210</ymax>
        </bndbox>
    </object>
    <object>
        <name>helmet-on</name>
        <pose>Unspecified</pose>
        <truncated>0</truncated>
        <difficult>0</difficult>
        <occluded>0</occluded>
        <bndbox>
            <xmin>586</xmin>
            <ymin>309</ymin>
            <xmax>772</xmax>
            <ymax>502</ymax>
        </bndbox>
    </object>
    <object>
        <name>helmet-on</name>
        <pose>Unspecified</pose>
        <truncated>0</truncated>
        <difficult>0</difficult>
        <occluded>0</occluded>
        <bndbox>
            <xmin>655</xmin>
            <ymin>104</ymin>
            <xmax>834</xmax>
            <ymax>282</ymax>
        </bndbox>
    </object>
    <object>
        <name>helmet-on</name>
        <pose>Unspecified</pose>
        <truncated>0</truncated>
        <difficult>0</difficult>
        <occluded>0</occluded>
        <bndbox>
            <xmin>244</xmin>
            <ymin>44</ymin>
            <xmax>430</xmax>
            <ymax>214</ymax>
        </bndbox>
    </object>
    <object>
        <name>person</name>
        <pose>Unspecified</pose>
        <truncated>0</truncated>
        <difficult>0</difficult>
        <occluded>0</occluded>
        <bndbox>
            <xmin>474</xmin>
            <ymin>305</ymin>
            <xmax>908</xmax>
            <ymax>719</ymax>
        </bndbox>
    </object>
    <object>
        <name>person</name>
        <pose>Unspecified</pose>
        <truncated>0</truncated>
        <difficult>0</difficult>
        <occluded>0</occluded>
        <bndbox>
            <xmin>657</xmin>
            <ymin>0</ymin>
            <xmax>1166</xmax>
            <ymax>528</ymax>
        </bndbox>
    </object>
    <object>
        <name>person</name>
        <pose>Unspecified</pose>
        <truncated>0</truncated>
        <difficult>0</difficult>
        <occluded>0</occluded>
        <bndbox>
            <xmin>507</xmin>
            <ymin>3</ymin>
            <xmax>740</xmax>
            <ymax>299</ymax>
        </bndbox>
    </object>
    <object>
        <name>person</name>
        <pose>Unspecified</pose>
        <truncated>0</truncated>
        <difficult>0</difficult>
        <occluded>0</occluded>
        <bndbox>
            <xmin>0</xmin>
            <ymin>444</ymin>
            <xmax>350</xmax>
            <ymax>719</ymax>
        </bndbox>
    </object>
    <object>
        <name>person</name>
        <pose>Unspecified</pose>
        <truncated>0</truncated>
        <difficult>0</difficult>
        <occluded>0</occluded>
        <bndbox>
            <xmin>0</xmin>
            <ymin>0</ymin>
            <xmax>429</xmax>
            <ymax>436</ymax>
        </bndbox>
    </object>
    <object>
        <name>helmet-off</name>
        <pose>Unspecified</pose>
        <truncated>0</truncated>
        <difficult>0</difficult>
        <occluded>0</occluded>
        <bndbox>
            <xmin>181</xmin>
            <ymin>450</ymin>
            <xmax>345</xmax>
            <ymax>613</ymax>
        </bndbox>
    </object>
</annotation>
